MANIFEST.in
README.rst
setup.py
blanc_basic_forms/__init__.py
blanc_basic_forms/forms.py
blanc_basic_forms/tests.py
blanc_basic_forms/urls.py
blanc_basic_forms/views.py
blanc_basic_forms.egg-info/PKG-INFO
blanc_basic_forms.egg-info/SOURCES.txt
blanc_basic_forms.egg-info/dependency_links.txt
blanc_basic_forms.egg-info/top_level.txt