Metadata-Version: 1.1
Name: blanc-basic-forms
Version: 0.1
Summary: Blanc Basic Forms for Django
Home-page: http://www.blanctools.com/
Author: Alex Tomkins
Author-email: alex@hawkz.com
License: BSD-2
Platform: any
Classifier: Environment :: Web Environment
Classifier: Framework :: Django
Classifier: License :: OSI Approved :: BSD License
Classifier: Operating System :: OS Independent
Classifier: Programming Language :: Python
